winix/__init__.py
winix/winixapi.py
winix/devices/__init__.py
winix/devices/purifier.py
winix/util/__init__.py
winix/util/cipher.py
winix/util/discovery.py
python_winix-0.1.4.dist-info/LICENSE
python_winix-0.1.4.dist-info/METADATA
python_winix-0.1.4.dist-info/WHEEL
python_winix-0.1.4.dist-info/top_level.txt
python_winix-0.1.4.dist-info/RECORD
