Metadata-Version: 2.1
Name: python-winix
Version: 0.1.4
Summary: A Python library for the Winix API
Home-page: UNKNOWN
Author: Evan Coleman
Author-email: oss@edc.me
License: UNKNOWN
Platform: UNKNOWN
Classifier: Programming Language :: Python :: 3
Classifier: License :: OSI Approved :: MIT License
Classifier: Operating System :: OS Independent
Requires-Dist: retrying
Requires-Dist: pycryptodome
